ckpt/__init__.py
ckpt/config.py
ckpt/decorator.py
ckpt/main.py
ckpt/run.py
ckpt/task.py
ckpt-0.2.3.dist-info/entry_points.txt
ckpt-0.2.3.dist-info/LICENSE
ckpt-0.2.3.dist-info/WHEEL
ckpt-0.2.3.dist-info/METADATA
ckpt-0.2.3.dist-info/RECORD
