Metadata-Version: 2.1
Name: ckpt
Version: 0.2.3
Summary: A package to create checkpoints in code for easier debugging.
Author-email: Holger Hoefling <hhoeflin@gmail.com>
Requires-Python: >=3.8
Classifier: License :: OSI Approved :: MIT License
Requires-Dist: typer >=0.4.0
Requires-Dist: cloudpickle >=0.3.4
Requires-Dist: pytest >=6.2.5 ; extra == "dev"
Requires-Dist: pytest-pudb >=0.7.0 ; extra == "dev"
Requires-Dist: pudb >=2021.2.2 ; extra == "dev"
Requires-Dist: ipython >=7.30.1 ; extra == "dev"
Requires-Dist: bpython >=0.22.1 ; extra == "dev"
Requires-Dist: ipdb >=0.13.9 ; extra == "dev"
Requires-Dist: Flake8-pyproject ; extra == "dev"
Project-URL: Home, https://hhoeflin.github.io/ckpt/
Provides-Extra: dev
